pymmcore_gui/__init__.py
pymmcore_gui/__main__.py
pymmcore_gui/_app.py
pymmcore_gui/_cli.py
pymmcore_gui/_main_window.py
pymmcore_gui/_ndv_viewers.py
pymmcore_gui/_notification_manager.py
pymmcore_gui/_sentry.py
pymmcore_gui/_settings.py
pymmcore_gui/_utils.py
pymmcore_gui/py.typed
pymmcore_gui/_qt/QtAds.py
pymmcore_gui/_qt/QtCore.py
pymmcore_gui/_qt/QtGui.py
pymmcore_gui/_qt/QtWidgets.py
pymmcore_gui/_qt/__init__.py
pymmcore_gui/actions/__init__.py
pymmcore_gui/actions/_action_info.py
pymmcore_gui/actions/_core_qaction.py
pymmcore_gui/actions/core_actions.py
pymmcore_gui/actions/widget_actions.py
pymmcore_gui/resources/icon.icns
pymmcore_gui/resources/icon.ico
pymmcore_gui/resources/logo.png
pymmcore_gui/resources/logo_trans.png
pymmcore_gui/widgets/__init__.py
pymmcore_gui/widgets/_about_widget.py
pymmcore_gui/widgets/_exception_log.py
pymmcore_gui/widgets/_mm_console.py
pymmcore_gui/widgets/_notifications.py
pymmcore_gui/widgets/_stage_control.py
pymmcore_gui/widgets/_toolbars.py
pymmcore_gui/widgets/image_preview/__init__.py
pymmcore_gui/widgets/image_preview/_ndv_preview.py
pymmcore_gui/widgets/image_preview/_preview_base.py
pymmcore_gui/widgets/image_preview/_pygfx_image.py
pymmcore_gui-0.0.1rc0.dist-info/METADATA
pymmcore_gui-0.0.1rc0.dist-info/WHEEL
pymmcore_gui-0.0.1rc0.dist-info/entry_points.txt
pymmcore_gui-0.0.1rc0.dist-info/licenses/LICENSE
pymmcore_gui-0.0.1rc0.dist-info/RECORD
