Metadata-Version: 2.4
Name: pymmcore-gui
Version: 0.0.1rc0
Summary: A Micro-Manager GUI based on pymmcore-widgets and pymmcore-plus.
Project-URL: homepage, https://github.com/tlambert03/pymmcore-gui
Project-URL: repository, https://github.com/tlambert03/pymmcore-gui
Author-email: Talley Lambert <talley.lambert@gmail.com>, Federico Gasparoli <federico.gasparoli@gmail.com>
License: BSD-3-Clause
License-File: LICENSE
Classifier: Development Status :: 3 - Alpha
Classifier: License :: OSI Approved :: BSD License
Classifier: Programming Language :: Python :: 3
Classifier: Programming Language :: Python :: 3.10
Classifier: Programming Language :: Python :: 3.11
Classifier: Programming Language :: Python :: 3.12
Classifier: Programming Language :: Python :: 3.13
Classifier: Typing :: Typed
Requires-Python: >=3.10
Requires-Dist: ndv[vispy]>=0.4.0
Requires-Dist: pydantic-settings>=2.7.1
Requires-Dist: pymmcore-plus[cli]>=0.13.2
Requires-Dist: pymmcore-widgets>=0.9.0
Requires-Dist: pymmcore==11.10.0.74.0
Requires-Dist: pyqt6==6.9.1
Requires-Dist: pyqt6ads==4.4.0.post2
Requires-Dist: pyyaml>=6.0.2
Requires-Dist: qtconsole>=5.6.1
Requires-Dist: rich
Requires-Dist: sentry-sdk>=2.20.0
Requires-Dist: superqt[cmap,iconify]>=0.7.1
Requires-Dist: tifffile>=2024.12.12
Requires-Dist: tqdm>=4.67.1
Requires-Dist: zarr<3.0,>=2.18.3
